pheval_template/__init__.py
pheval_template/post_process/__init__.py
pheval_template/post_process/post_process.py
pheval_template/post_process/post_process_results_format.py
pheval_template/prepare/__init__.py
pheval_template/run/__init__.py
pheval_template/run/fake_predictor.py
pheval_template/run/run.py
pheval_template/run/run_tool.py
pheval_template/runner.py
pheval_template-0.2.0.dist-info/METADATA
pheval_template-0.2.0.dist-info/WHEEL
pheval_template-0.2.0.dist-info/entry_points.txt
pheval_template-0.2.0.dist-info/RECORD
